zamm/__init__.py
zamm/actions/__init__.py
zamm/actions/base.py
zamm/actions/edit_file/__init__.py
zamm/actions/edit_file/action.py
zamm/actions/edit_file/chain.py
zamm/actions/edit_file/filesystem.py
zamm/actions/edit_file/prompt.py
zamm/actions/finish.py
zamm/actions/follow_tutorial/__init__.py
zamm/actions/follow_tutorial/action.py
zamm/actions/follow_tutorial/chain.py
zamm/actions/follow_tutorial/prompt.py
zamm/actions/note/__init__.py
zamm/actions/note/action.py
zamm/actions/note/chain.py
zamm/actions/note/prompt.py
zamm/actions/use_terminal/__init__.py
zamm/actions/use_terminal/action.py
zamm/actions/use_terminal/chain.py
zamm/actions/use_terminal/prompt.py
zamm/actions/use_terminal/terminal.py
zamm/agents/__init__.py
zamm/agents/base.py
zamm/agents/employee.py
zamm/agents/employee_actions.py
zamm/agents/memory.py
zamm/agents/step.py
zamm/agents/z_step.py
zamm/chains/__init__.py
zamm/chains/ask_task.py
zamm/chains/bash_action_prompt.py
zamm/chains/bash_chain.py
zamm/chains/dummy.py
zamm/chains/general/__init__.py
zamm/chains/general/action_chain.py
zamm/chains/general/boolean_switch.py
zamm/chains/general/choice/__init__.py
zamm/chains/general/choice/base.py
zamm/chains/general/choice/prompt.py
zamm/chains/general/error.py
zamm/chains/general/get_dict/__init__.py
zamm/chains/general/get_dict/base.py
zamm/chains/general/get_dict/config.py
zamm/chains/general/get_dict/prompt.py
zamm/chains/general/lax_sequential.py
zamm/chains/general/llm.py
zamm/chains/general/no_op.py
zamm/chains/general/options_chain.py
zamm/chains/human_cmd_review.py
zamm/chains/success_chain.py
zamm/chains/success_criteria.py
zamm/cli.py
zamm/llms/__init__.py
zamm/llms/chat.py
zamm/llms/fake.py
zamm/llms/human.py
zamm/prompts/__init__.py
zamm/prompts/chained.py
zamm/prompts/dummy.py
zamm/prompts/fake_parser.py
zamm/prompts/parser.py
zamm/prompts/prefixed.py
zamm/resources/__init__.py
zamm/resources/tutorials/__init__.py
zamm/resources/tutorials/add-action.md
zamm-0.0.5.dist-info/METADATA
zamm-0.0.5.dist-info/WHEEL
zamm-0.0.5.dist-info/LICENSE
zamm-0.0.5.dist-info/entry_points.txt
zamm-0.0.5.dist-info/RECORD
