Metadata-Version: 2.1
Name: zamm
Version: 0.0.5
Summary: General automation driver
Author: Amos Jun-yeung Ng
Author-email: me@amos.ng
Requires-Python: >=3.9,<4.0
Classifier: Programming Language :: Python :: 3
Classifier: Programming Language :: Python :: 3.9
Classifier: Programming Language :: Python :: 3.10
Classifier: Programming Language :: Python :: 3.11
Requires-Dist: appdirs (>=1.4.4,<2.0.0)
Requires-Dist: langchain-visualizer (>=0.0.14,<0.0.15)
Requires-Dist: openai (>=0.27.0,<0.28.0)
Requires-Dist: pexpect (>=4.8.0,<5.0.0)
Requires-Dist: pyyaml (>=6.0,<7.0)
Requires-Dist: simple-term-menu (>=1.6.1,<2.0.0)
Requires-Dist: tiktoken (>=0.2.0,<0.3.0)
Requires-Dist: typer[all] (>=0.7.0,<0.8.0)
Requires-Dist: ulid (>=1.1,<2.0)
Requires-Dist: vcr-langchain (>=0.0.17,<0.0.18)
